{"id":"login.html","dependencies":[{"name":"/Users/lronelove/Documents/learning/egg/package.json","includedInParent":true,"mtime":1539956226450},{"name":"./login.js","dynamic":true,"parent":"/Users/lronelove/Documents/learning/egg/web/login.html","resolved":"/Users/lronelove/Documents/learning/egg/web/login.js"}],"generated":{"html":"<!DOCTYPE html>\n<html lang=\"en\">\n<head>\n  <meta charset=\"UTF-8\">\n  <meta name=\"viewport\" content=\"width=device-width, initial-scale=1.0\">\n  <meta http-equiv=\"X-UA-Compatible\" content=\"ie=edge\">\n  <title>login</title>\n  <style>\n    * {\n      margin: 0;\n      padding: 0;\n      box-sizing: border-box;\n    }\n    #submit {\n      border: none;\n      background: lightblue;\n      outline: none;\n      text-align: center;\n      font-size: 18px;\n      padding: 5px 20px;\n      margin-top: 50px;\n      margin-left: 220px;\n      cursor: pointer;\n      border-radius: 4px;\n    }\n    label {\n      margin: 10px;\n      padding: 10px;\n    }\n  </style>\n</head>\n<body>\n  <div id=\"form\">\n    <label for=\"username\">\n      <span>用户名：</span>\n      <input type=\"text\" placeholder=\"用户名\" id=\"username\">\n    </label>\n    <label for=\"password\">\n      <span>密码：</span>\n      <input type=\"text\" placeholder=\"密码\" id=\"password\">\n    </label>\n    <br>\n    <button id=\"submit\">登陆</button>\n  </div>\n\n  <script src=\"/b685c2f78a31274e4bb2843e2426b12a.js\"></script>\n</body>\n</html>"},"hash":"4e5ba43d68c41a06d5a9190fd4888765","cacheData":{}}